timeanalysismoon/__init__.py
timeanalysismoon/decorator.py
timeanalysismoon-0.9.3.dist-info/METADATA
timeanalysismoon-0.9.3.dist-info/WHEEL
timeanalysismoon-0.9.3.dist-info/top_level.txt
timeanalysismoon-0.9.3.dist-info/RECORD
