Metadata-Version: 2.1
Name: timeanalysismoon
Version: 0.9.3
Summary: A time analysis decorator for Python functions
Home-page: https://github.com/CoderMungan/timeanalysismoon
Author: CoderMungan
Author-email: codermungan@gmail.com
Classifier: License :: OSI Approved :: MIT License
Classifier: Programming Language :: Python :: 3.6
Classifier: Programming Language :: Python :: 3.7
Classifier: Programming Language :: Python :: 3.8
Classifier: Programming Language :: Python :: 3.9
Classifier: Programming Language :: Python :: 3.10
Classifier: Programming Language :: Python :: 3.11
Classifier: Programming Language :: Python :: 3.12
